fluxiondb/__init__.py
fluxiondb/main.py
fluxiondb/types.py
fluxiondb-0.0.1.dist-info/LICENSE
fluxiondb-0.0.1.dist-info/METADATA
fluxiondb-0.0.1.dist-info/WHEEL
fluxiondb-0.0.1.dist-info/RECORD
