Metadata-Version: 2.3
Name: fluxiondb
Version: 0.0.1
Summary: Python client for Fluxion
Author: seyedasfar
Author-email: seyed.asfar@outlook.com
Requires-Python: >=3.12
Classifier: Programming Language :: Python :: 3
Classifier: Programming Language :: Python :: 3.12
Classifier: Programming Language :: Python :: 3.13
